LICENSE
README.md
kasutils.py
kasutils-0.0.2.dist-info/LICENSE
kasutils-0.0.2.dist-info/METADATA
kasutils-0.0.2.dist-info/WHEEL
kasutils-0.0.2.dist-info/RECORD
