Metadata-Version: 2.1
Name: kasutils
Version: 0.0.2
Summary: My utility library with zero dependency
Home-page: https://github.com/KasRoudra2/kasutils/
License: MIT
Author: KasRoudra
Author-email: kasroudrakrd@gmail.com
Requires-Python: >=3.9,<4.0
Classifier: License :: OSI Approved :: MIT License
Classifier: Programming Language :: Python :: 3
Classifier: Programming Language :: Python :: 3.9
Classifier: Programming Language :: Python :: 3.10
Classifier: Programming Language :: Python :: 3.11
Project-URL: Repository, https://github.com/KasRoudra2/kasutils/
